{
	"info": {
		"_postman_id": "762a5640-d728-4348-a650-5cfad4b4559c",
		"name": "Inventory",
		"schema": "https://schema.getpostman.com/json/collection/v2.1.0/collection.json",
		"_exporter_id": "1814662"
	},
	"item": [
		{
			"name": "Product",
			"item": [
				{
					"name": "Index",
					"request": {
						"method": "GET",
						"header": [
							{
								"key": "Content-Type",
								"value": "application/json",
								"type": "text"
							},
							{
								"key": "Accept",
								"value": "application/json",
								"type": "text"
							}
						],
						"url": {
							"raw": "{{inventory_url}}/products",
							"host": [
								"{{inventory_url}}"
							],
							"path": [
								"products"
							]
						}
					},
					"response": []
				},
				{
					"name": "Detail",
					"request": {
						"method": "GET",
						"header": [
							{
								"key": "Accept",
								"value": "application/json",
								"type": "text"
							},
							{
								"key": "Content-Type",
								"value": "application/json",
								"type": "text"
							}
						],
						"url": {
							"raw": "{{inventory_url}}/products/1",
							"host": [
								"{{inventory_url}}"
							],
							"path": [
								"products",
								"1"
							]
						}
					},
					"response": []
				},
				{
					"name": "Store",
					"request": {
						"method": "POST",
						"header": [
							{
								"key": "Accept",
								"value": "application/json",
								"type": "text"
							},
							{
								"key": "Content-Type",
								"value": "application/json",
								"type": "text"
							}
						],
						"body": {
							"mode": "raw",
							"raw": "{\n    \"name\": \"Product C\",\n    \"qty\": 500\n}"
						},
						"url": {
							"raw": "{{inventory_url}}/products",
							"host": [
								"{{inventory_url}}"
							],
							"path": [
								"products"
							]
						}
					},
					"response": []
				},
				{
					"name": "Update",
					"request": {
						"method": "PUT",
						"header": [
							{
								"key": "Content-Type",
								"value": "application/json",
								"type": "text"
							},
							{
								"key": "Accept",
								"value": "application/json",
								"type": "text"
							}
						],
						"body": {
							"mode": "raw",
							"raw": "{\n    \"name\": \"Product B\",\n    \"qty\": 2\n}"
						},
						"url": {
							"raw": "{{inventory_url}}/products/4",
							"host": [
								"{{inventory_url}}"
							],
							"path": [
								"products",
								"4"
							]
						}
					},
					"response": []
				},
				{
					"name": "Delete",
					"request": {
						"method": "DELETE",
						"header": [
							{
								"key": "Content-Type",
								"value": "application/json",
								"type": "text"
							},
							{
								"key": "Accept",
								"value": "application/json",
								"type": "text"
							}
						],
						"url": {
							"raw": "{{inventory_url}}/products/4",
							"host": [
								"{{inventory_url}}"
							],
							"path": [
								"products",
								"4"
							]
						}
					},
					"response": []
				}
			]
		},
		{
			"name": "Supplier",
			"item": [
				{
					"name": "Index",
					"request": {
						"method": "GET",
						"header": [
							{
								"key": "Content-Type",
								"value": "application/json",
								"type": "text"
							},
							{
								"key": "Accept",
								"value": "application/json",
								"type": "text"
							}
						],
						"url": {
							"raw": "{{inventory_url}}/suppliers",
							"host": [
								"{{inventory_url}}"
							],
							"path": [
								"suppliers"
							]
						}
					},
					"response": []
				},
				{
					"name": "Detail",
					"request": {
						"method": "GET",
						"header": [
							{
								"key": "Accept",
								"value": "application/json",
								"type": "text"
							},
							{
								"key": "Content-Type",
								"value": "application/json",
								"type": "text"
							}
						],
						"url": {
							"raw": "{{inventory_url}}/suppliers/4",
							"host": [
								"{{inventory_url}}"
							],
							"path": [
								"suppliers",
								"4"
							]
						}
					},
					"response": []
				},
				{
					"name": "Store",
					"request": {
						"method": "POST",
						"header": [
							{
								"key": "Accept",
								"value": "application/json",
								"type": "text"
							},
							{
								"key": "Content-Type",
								"value": "application/json",
								"type": "text"
							}
						],
						"body": {
							"mode": "raw",
							"raw": "{\n    \"name\": \"Supplier A\"\n}"
						},
						"url": {
							"raw": "{{inventory_url}}/suppliers",
							"host": [
								"{{inventory_url}}"
							],
							"path": [
								"suppliers"
							]
						}
					},
					"response": []
				},
				{
					"name": "Update",
					"request": {
						"method": "PUT",
						"header": [
							{
								"key": "Content-Type",
								"value": "application/json",
								"type": "text"
							},
							{
								"key": "Accept",
								"value": "application/json",
								"type": "text"
							}
						],
						"body": {
							"mode": "raw",
							"raw": "{\n    \"name\": \"Supplier B\"\n}"
						},
						"url": {
							"raw": "{{inventory_url}}/suppliers/4",
							"host": [
								"{{inventory_url}}"
							],
							"path": [
								"suppliers",
								"4"
							]
						}
					},
					"response": []
				},
				{
					"name": "Delete",
					"request": {
						"method": "DELETE",
						"header": [
							{
								"key": "Content-Type",
								"value": "application/json",
								"type": "text"
							},
							{
								"key": "Accept",
								"value": "application/json",
								"type": "text"
							}
						],
						"url": {
							"raw": "{{inventory_url}}/suppliers/4",
							"host": [
								"{{inventory_url}}"
							],
							"path": [
								"suppliers",
								"4"
							]
						}
					},
					"response": []
				}
			]
		},
		{
			"name": "Purchase",
			"item": [
				{
					"name": "Index",
					"request": {
						"method": "GET",
						"header": [
							{
								"key": "Content-Type",
								"value": "application/json",
								"type": "text"
							},
							{
								"key": "Accept",
								"value": "application/json",
								"type": "text"
							}
						],
						"url": {
							"raw": "{{inventory_url}}/purchases",
							"host": [
								"{{inventory_url}}"
							],
							"path": [
								"purchases"
							]
						}
					},
					"response": []
				},
				{
					"name": "Detail",
					"request": {
						"method": "GET",
						"header": [
							{
								"key": "Accept",
								"value": "application/json",
								"type": "text"
							},
							{
								"key": "Content-Type",
								"value": "application/json",
								"type": "text"
							}
						],
						"url": {
							"raw": "{{inventory_url}}/purchases/1",
							"host": [
								"{{inventory_url}}"
							],
							"path": [
								"purchases",
								"1"
							]
						}
					},
					"response": []
				},
				{
					"name": "Store",
					"request": {
						"method": "POST",
						"header": [
							{
								"key": "Accept",
								"value": "application/json",
								"type": "text"
							},
							{
								"key": "Content-Type",
								"value": "application/json",
								"type": "text"
							}
						],
						"body": {
							"mode": "raw",
							"raw": "{\n    \"qty\": 10,\n    \"date\": \"2023-07-03 13:00:00\",\n    \"product_id\": 5,\n    \"supplier_id\": 5\n}"
						},
						"url": {
							"raw": "{{inventory_url}}/purchases",
							"host": [
								"{{inventory_url}}"
							],
							"path": [
								"purchases"
							]
						}
					},
					"response": []
				},
				{
					"name": "Update",
					"request": {
						"method": "PUT",
						"header": [
							{
								"key": "Content-Type",
								"value": "application/json",
								"type": "text"
							},
							{
								"key": "Accept",
								"value": "application/json",
								"type": "text"
							}
						],
						"body": {
							"mode": "raw",
							"raw": "{\n    \"qty\": 200,\n    \"date\": \"2023-07-01 13:00:00\",\n    \"product_id\": 5,\n    \"supplier_id\": 5\n}"
						},
						"url": {
							"raw": "{{inventory_url}}/purchases/5",
							"host": [
								"{{inventory_url}}"
							],
							"path": [
								"purchases",
								"5"
							]
						}
					},
					"response": []
				},
				{
					"name": "Delete",
					"request": {
						"method": "DELETE",
						"header": [
							{
								"key": "Content-Type",
								"value": "application/json",
								"type": "text"
							},
							{
								"key": "Accept",
								"value": "application/json",
								"type": "text"
							}
						],
						"url": {
							"raw": "{{inventory_url}}/purchases/5",
							"host": [
								"{{inventory_url}}"
							],
							"path": [
								"purchases",
								"5"
							]
						}
					},
					"response": []
				}
			]
		}
	]
}